LICENSE
README.md
setup.py
web_stable_diffusion/__init__.py
web_stable_diffusion/utils.py
web_stable_diffusion.egg-info/PKG-INFO
web_stable_diffusion.egg-info/SOURCES.txt
web_stable_diffusion.egg-info/dependency_links.txt
web_stable_diffusion.egg-info/requires.txt
web_stable_diffusion.egg-info/top_level.txt
web_stable_diffusion/trace/__init__.py
web_stable_diffusion/trace/model_trace.py
web_stable_diffusion/trace/scheduler_trace.py